emoji_meaning/__init__.py
emoji_meaning-0.1.dist-info/LICENCE.txt
emoji_meaning-0.1.dist-info/METADATA
emoji_meaning-0.1.dist-info/WHEEL
emoji_meaning-0.1.dist-info/top_level.txt
emoji_meaning-0.1.dist-info/RECORD
