Metadata-Version: 2.1
Name: emoji-meaning
Version: 0.1
Summary: This is give emoji meaning
Author: Rajkumar
Author-email: poonkuzhaliraj123@gmail.com
Classifier: Programming Language :: Python :: 3
Classifier: License :: OSI Approved :: MIT License
Classifier: Operating System :: OS Independent
License-File: LICENCE.txt
